pkboost-2.2.2.dist-info/METADATA
pkboost-2.2.2.dist-info/WHEEL
pkboost-2.2.2.dist-info/licenses/LICENSE
pkboost-2.2.2.dist-info/licenses/LICENSE-GPL
pkboost/__init__.py
pkboost/pkboost.cp314-win_amd64.pyd
pkboost_sklearn/__init__.py
pkboost_sklearn/classifier.py
pkboost_sklearn/multiclass.py
pkboost_sklearn/regressor.py
pkboost_sklearn/sklearn_interface.py
pkboost_sklearn/test_sklearn_compat.py
pkboost-2.2.2.dist-info/RECORD
