Metadata-Version: 2.4
Name: pkboost
Version: 2.2.2
Classifier: Programming Language :: Rust
Classifier: Programming Language :: Python :: Implementation :: CPython
Classifier: Programming Language :: Python :: 3.8
Classifier: Programming Language :: Python :: 3.9
Classifier: Programming Language :: Python :: 3.10
Classifier: Programming Language :: Python :: 3.11
Classifier: Programming Language :: Python :: 3.12
Requires-Dist: numpy>=1.24.0
Requires-Dist: scikit-learn>=1.0.0 ; extra == 'sklearn'
Provides-Extra: sklearn
License-File: LICENSE
License-File: LICENSE-GPL
Summary: Gradient boosting that adapts to concept drift in imbalanced data
Home-Page: https://github.com/Pushp-Kharat1/pkboost
Author-email: Pushp Kharat <kharatpushp16@outlook.com>
Requires-Python: >=3.8
Project-URL: Homepage, https://pkboost.vercel.app/
Project-URL: Repository, https://github.com/Pushp-Kharat1/pkboost
